{
  "Path": "cpuminer-$($f=$SystemInfo.CpuFeatures;$(if($f.avx2 -and $f.sha){'zen'}elseif($f.avx2){'avx2'}elseif($f.avx){'avx'}elseif($f.aes -and $f.sse42){'aes-sse42'}else{'sse2'})).exe",
  "Uri": "https://github.com/JayDDee/cpuminer-opt/releases/download/v3.9.5.4/cpuminer-opt-3.9.5.4-windows.zip",
  "SHA256": "4013A014E9592E337A30B9E8216F6A71FAEF8ECC47332B1A19F386FF2965BF8B",
  "Type": "CPU",
  "Arguments": [
    "-o #Protocol#://#Server#:#Port#",
    "-u #Login#",
    "-p #Password#",
    "-R 3",
    "-r 10",
    "-b #APIPort#",
    "$(if ($CpuThreads -ne $null){'-t ' + $CpuThreads})",
    "#AlgorithmParameters#",
    "#CustomParameters#"
  ],
  "API": "Ccminer",
  "Algorithms": {
    "HOdl": "-a hodl",
    "Lyra2h": "-a lyra2h",
    "Lyra2z330": "-a lyra2z330",
    "M7M": "-a m7m",
    "Scrypt8k": "-a scrypt:8192",
    "ScryptN": "-a scrypt:2048",
    "ScryptJane16": "-a scryptjane:16",
    "Verium": "-a scrypt:1048576",
    "Yescrypt": "-a yescrypt",
    "Yespower": "-a yespower",
    "YespowerR16": "-a yespowerr16"
  }
}
