{
  "Path": "Claymore's Dual Ethereum+Decred_Siacoin_Lbry_Pascal_Blake2s_Keccak AMD+NVIDIA GPU Miner v12.0 - LINUX/ethdcrminer64",
  "Uri": "https://github.com/yuzi-co/miners-linux/releases/download/2019.03/Claymore.s.Dual.Ethereum+Decred_Siacoin_Lbry_Pascal_Blake2s_Keccak.AMD+NVIDIA.GPU.Miner.v12.0.-.LINUX.tar.gz",
  "SHA256": "CA31C54843AD00FC4514AF8CD19E6CE9D8FD1F816C13497135AB9387E1DD21F7",
  "Type": "_AMD",
  "Arguments": [
    "-epool #Protocol#://#Server#:#Port#",
    "-ewal #Login#",
    "-epsw #Password#",
    "-esm #EthStMode#",
    "-dpool #ProtocolDual#://#ServerDual#:#PortDual#",
    "-dwal #LoginDual#",
    "-dpsw #PasswordDual#",
    "-wd 1",
    "-r -1",
    "-logfile #GroupName#_log.txt",
    "-logsmaxsize 10",
    "-platform 1",
    "-mport -#APIPort#",
    "-allpools 1",
    "#AlgorithmParameters#"
  ],
  "API": "Claymore",
  "APIPort": 4028,
  "Fee": "$(if ($DeviceGroup.MemoryGB -gt 3){0.01}else{0})",
  "SSL": true,
  "Algorithms": {
    "Ethash|a1": "-asm 1 -mode 1",
    "Ethash|a2": "-asm 2 -mode 1",
    "Ethash_Blake2s|50": "-dcoin blake2s -dcri 50 -mode 0",
    "Ethash_Blake2s|55": "-dcoin blake2s -dcri 55 -mode 0",
    "Ethash_Blake2s|60": "-dcoin blake2s -dcri 60 -mode 0",
    "Ethash_Keccak|06": "-dcoin keccak -dcri 6 -mode 0",
    "Ethash_Keccak|07": "-dcoin keccak -dcri 7 -mode 0",
    "Ethash_Keccak|08": "-dcoin keccak -dcri 8 -mode 0",
    "_Ethash_Decred|30": "-dcoin dcr -dcri 30 -mode 0",
    "_Ethash_Decred|35": "-dcoin dcr -dcri 35 -mode 0",
    "_Ethash_Lbry|25": "-dcoin lbc -dcri 25 -mode 0",
    "_Ethash_Lbry|35": "-dcoin lbc -dcri 35 -mode 0",
    "_Ethash_Pascal|10": "-dcoin pasc -dcri 10 -mode 0",
    "_Ethash_Pascal|15": "-dcoin pasc -dcri 15 -mode 0"
  }
}
