{
  "Path": "CryptoDredge_0.17.0/CryptoDredge",
  "Uri": "https://github.com/technobyl/CryptoDredge/releases/download/v0.17.0/CryptoDredge_0.17.0_cuda_10.0_linux.tar.gz",
  "SHA256": "94D63FAA2640318F038455B98CC8534000F077E8BF132B6E7A8614D320803052",
  "Type": "NVIDIA",
  "Arguments": [
    "-o #Protocol#://#Server#:#Port#",
    "-u #Login#",
    "-p #Password#",
    "-d #Devices#",
    "--retries 4",
    "--retry-pause 10",
    "--timeout 5",
    "--no-watchdog",
    "-b 127.0.0.1:#APIPort#",
    "#AlgorithmParameters#",
    "#CustomParameters#"
  ],
  "API": "Ccminer",
  "Fee": 0.01,
  "CUDA": 10.0,
  "Custom": "--intensity 8",
  "Algorithms": {
    "Cuckoo29": {
      "Params": "-a aeternity",
      "Mem": 5.6
    },
    "Allium": "-a allium",
    "BCD": "-a bcd",
    "Bitcore": "-a bitcore",
    "C11": "-a c11",
    "CnFast": "-a cnfast",
    "CnGpu": "-a cngpu ",
    "CnHalf": "-a cnfast2",
    "CnHaven": "-a cnhaven",
    "CnHeavy": "-a cnheavy",
    "CnLiteV7": "-a aeon",
    "CnSaber": "-a cnsaber",
    "CnTurtle": "-a cnturtle",
    "_CnV7": "-a cnv7",
    "_CnV8": "-a cnv8",
    "CnWow": "-a cnsuperfast",
    "CnXTL": "-a stellite",
    "Cuckaroo29": {
      "Params": "-a cuckaroo29",
      "NoCpu": true,
      "Mem": 5.6,
      "NH": false
    },
    "Dedal": "-a dedal",
    "Hmq1725": "-a hmq1725",
    "Lyra2v3": "-a lyra2rev3",
    "Lyra2vc0ban": "-a lyra2vc0banhash",
    "Lyra2z": "-a lyra2z",
    "Lyra2zz": "-a lyra2zz",
    "MTP": {
      "Params": "-a mtp",
      "NH": false,
      "Mem": 4.5,
      "Fee": 0.02
    },
    "NeoScrypt": {
      "Params": "-a neoscrypt",
      "Custom": "--intensity 6"
    },
    "Phi": "-a phi",
    "Phi2": "-a phi2",
    "Pipe ": "-a pipe",
    "Skunk": "-a skunk",
    "Tribus": "-a tribus",
    "X16r": "-a x16r",
    "X16rt": "-a x16rt",
    "X16s": "-a x16s",
    "X17": "-a x17",
    "X21s": "-a x21s",
    "X22i": "-a x22i"
  }
}
