{
    "Path": "cast_xmr-vega.exe",
    "Uri": "http://www.gandalph3000.com/download/cast_xmr-vega-win64_160.zip",
    "SHA256": "ECC857C039DABF648FE6E823069CFCAA3988A20BA41E35057A3EE47640F04B9A",
    "Type": "AMD",
    "Arguments": [
        "--pool #Server#:#Port#",
        "--user #Login#",
        "--password #Password#",
        "--remoteaccess",
        "--remoteport #APIPort#",
        "--opencl #GPUPlatform#",
        "--gpu #Devices#",
        "--ratewatchdog",
        "$(if (-not $Nicehash){'--nonicehash'})",
        "#AlgorithmParameters#"
    ],
    "API": "castXMR",
    "APIPort": 4028,
    "Fee": 0.015,
    "Algorithms": {
        "CnFast": "--algo=8",
        "CnFеst": "--algo=9",
        "CnHaven": "--algo=7",
        "CnHeavy": "--algo=2",
        "CnLiteV7": "--algo=4",
        "CnSaber": "--algo=5",
        "CnV7": "--algo=1",
        "CnV8": "--algo=-1",
        "CnXTL": "--algo=6"
    }
}